yt_dlp_ejs/__init__.py
yt_dlp_ejs/_version.py
yt_dlp_ejs/yt/__init__.py
yt_dlp_ejs/yt/solver/__init__.py
yt_dlp_ejs/yt/solver/core.min.js
yt_dlp_ejs/yt/solver/lib.min.js
yt_dlp_ejs-0.2.1.dist-info/METADATA
yt_dlp_ejs-0.2.1.dist-info/WHEEL
yt_dlp_ejs-0.2.1.dist-info/licenses/LICENSE
yt_dlp_ejs-0.2.1.dist-info/RECORD
