Metadata-Version: 2.4
Name: yt-dlp-ejs
Version: 0.2.1
Summary: External JavaScript for yt-dlp supporting many runtimes
Project-URL: Documentation, https://github.com/yt-dlp/ejs#readme
Project-URL: Issues, https://github.com/yt-dlp/ejs/issues
Project-URL: Source, https://github.com/yt-dlp/ejs
Author-email: Simon Sawicki <contact@grub4k.dev>
License-Expression: Unlicense AND MIT AND ISC
License-File: LICENSE
Keywords: yt-dlp
Classifier: Development Status :: 5 - Production/Stable
Classifier: Programming Language :: Python
Classifier: Programming Language :: Python :: 3.10
Classifier: Programming Language :: Python :: 3.11
Classifier: Programming Language :: Python :: 3.12
Classifier: Programming Language :: Python :: 3.13
Classifier: Programming Language :: Python :: 3.14
Classifier: Programming Language :: Python :: Implementation :: CPython
Classifier: Programming Language :: Python :: Implementation :: PyPy
Requires-Python: >=3.10
